<parameters>
    <required/>
    <optional/>
    <external>
        <ant-junit>
            <dir>ant-junit-1.6.5</dir>
            <file>ant-junit-1.6.5.jar</file>
            <url>http://mirrors.ibiblio.org/pub/mirrors/maven2/ant/ant-junit/1.6.5/ant-junit-1.6.5.jar</url>
        </ant-junit>
        <cc>
            <dir>cruisecontrol_2.6.1</dir>
            <file>cruisecontrol.zip</file>
            <url>http://umn.dl.sourceforge.net/sourceforge/cruisecontrol/cruisecontrol-bin-2.5.zip</url>
        </cc>
    </external>
</parameters>

